brt_classifier/__init__.py
brt_classifier/__main__.py
brt_classifier/classify.py
brt_classifier/complexity.py
brt_classifier/generateProblems.py
brt_classifier/getProblem.py
brt_classifier/statistics.py
brt_classifier/util.py
brt_classifier/postprocess/findByExpDecider.py
brt_classifier/postprocess/findContradictionsByDecider.py
brt_classifier/postprocess/findExtremeBoundCases.py
brt_classifier/postprocess/findLogLowerBounds.py
brt_classifier/postprocess/findLowerBounds.py
brt_classifier/postprocess/findLowerBoundsByReplacement.py
brt_classifier/postprocess/findMaximal.py
brt_classifier/postprocess/findMinimal.py
brt_classifier/postprocess/findRootOnlyParents.py
brt_classifier/postprocess/findSolvable.py
brt_classifier/postprocess/findUpperBounds.py
brt_classifier/postprocess/postprocess.py
brt_classifier/problems/2labels.json
brt_classifier/problems/3labels.json
brt_classifier-0.1.14.data/data/data/2labels.json
brt_classifier-0.1.14.data/data/data/3labels.json
brt_classifier-0.1.14.dist-info/METADATA
brt_classifier-0.1.14.dist-info/WHEEL
brt_classifier-0.1.14.dist-info/top_level.txt
brt_classifier-0.1.14.dist-info/RECORD
