Metadata-Version: 2.1
Name: brt-classifier
Version: 0.1.14
Summary: A command-line tool for automatically classifying binary and ternary labelling problems on bipartite rooted trees (hence BRT).
Home-page: https://github.com/AleksTeresh/tree-classifications
Author: Aleksandr Tereshchenko
Author-email: aleksandr.tereshch@gmail.com
License: MIT
Platform: UNKNOWN
Classifier: License :: OSI Approved :: MIT License
Classifier: Programming Language :: Python :: 3
Classifier: Programming Language :: Python :: 3.8
